{
	"title" : "Top 10 Trails You Have To Hike Before You Die",
	"bodyClass": "article",
	"author" : {
		"first-name" : "Julianne",
		"last-name" : "McCormick"
	},
	"img": {
		"feature-image": {
			"src": "../../assets/images/sample/landscape-feature-image-mountains.jpg",
			"alt": "Mountains"
		},
		"feature-thumb": {
			"src": "../../assets/images/sample/landscape-feature-thumb-mountains.jpg",
			"alt": "Mountains"
		}
	},
	"inset-blocks" : [
		{
			"headline" : "This is the headline for the inset block"
		}
	],
	"latest-block" : [
		{
			"headline" : "This is the headline for the latest block"
		}
	]
}